<layer>
  <name>SpeciesObservationsInvasive</name>
  <id>LayerInfoImpl--5811225:18a937978c2:-7904</id>
  <type>VECTOR</type>
  <defaultStyle>
    <id>StyleInfoImpl-1b348ea4:18488e85cd3:-700c</id>
  </defaultStyle>
  <styles class="linked-hash-set">
    <style>
      <id>StyleInfoImpl--2c64b10:184804c62a5:-6295</id>
    </style>
    <style>
      <id>StyleInfoImpl-1b348ea4:18488e85cd3:-700c</id>
    </style>
    <style>
      <id>StyleInfoImpl--2c64b10:184804c62a5:-6280</id>
    </style>
    <style>
      <id>StyleInfoImpl--2c64b10:184804c62a5:-623a</id>
    </style>
    <style>
      <id>StyleInfoImpl-1b348ea4:18488e85cd3:-6fd6</id>
    </style>
    <style>
      <id>StyleInfoImpl--2c64b10:184804c62a5:-62a1</id>
    </style>
    <style>
      <id>StyleInfoImpl--2c64b10:184804c62a5:-629c</id>
    </style>
    <style>
      <id>StyleInfoImpl--2c64b10:184804c62a5:-62a5</id>
    </style>
    <style>
      <id>StyleInfoImpl--2c64b10:184804c62a5:-6263</id>
    </style>
    <style>
      <id>StyleInfoImpl--2c64b10:184804c62a5:-6298</id>
    </style>
    <style>
      <id>StyleInfoImpl--2c64b10:184804c62a5:-7fff</id>
    </style>
    <style>
      <id>StyleInfoImpl--2c64b10:184804c62a5:-629f</id>
    </style>
  </styles>
  <resource class="featureType">
    <id>FeatureTypeInfoImpl--5811225:18a937978c2:-7905</id>
  </resource>
  <attribution>
    <logoWidth>0</logoWidth>
    <logoHeight>0</logoHeight>
  </attribution>
  <dateCreated>2023-09-14 11:59:57.871 UTC</dateCreated>
  <dateModified>2023-09-14 13:00:45.906 UTC</dateModified>
</layer>